WebSniffer/__init__.py
WebSniffer/scrapper.py
WebSniffer-0.3.dist-info/METADATA
WebSniffer-0.3.dist-info/WHEEL
WebSniffer-0.3.dist-info/top_level.txt
WebSniffer-0.3.dist-info/RECORD
